{
  "name": "BCPC-Hadoop-Head-HBase",
  "json_class": "Chef::Role",
  "run_list": [
    "role[Basic]",
    "recipe[bcpc-hadoop::hbase_repl]",
    "recipe[bcpc-hadoop::hbase_master]",
    "recipe[bcpc::diamond]"
  ],
  "description": "A highly-available head node in a BCPC Hadoop cluster",
  "chef_type": "role",
  "default_attributes" : {
    "jmxtrans":  {
      "servers":  [
                 {
                    "type": "hbase_master",
                    "service": "hbase-master",
                    "service_cmd": "org.apache.hadoop.hbase.master.HMaster"
                 }
        ]
      }
  },
  "override_attributes": {
  }
}
